<?xml version="1.0" encoding="utf-8"?>
<!DOCTYPE hibernate-mapping PUBLIC "-//Hibernate/Hibernate Mapping DTD 3.0//EN"
"http://hibernate.sourceforge.net/hibernate-mapping-3.0.dtd">
<!-- 
    Mapping file autogenerated by MyEclipse Persistence Tools
-->
<hibernate-mapping>
    <class name="cn.dinner.entity.DiningTable" table="dining_table">
        <id name="id" type="java.lang.Integer">
            <column name="ID" precision="6" scale="0" />
            <generator class="identity" />
        </id>
        <property name="tableNum" type="java.lang.String">
            <column name="TABLE_NUM" length="40" not-null="true" />
        </property>
        <property name="tablePernum" type="java.lang.Integer">
            <column name="TABLE_PERNUM" precision="6" scale="0" not-null="true" />
        </property>
        <property name="isno" type="java.lang.Integer">
            <column name="ISNO" precision="6" scale="0" not-null="true" />
        </property>
    </class>
</hibernate-mapping>
